{
  "project_info": {
    "project_number": "1063702941408",
    "project_id": "myshopping-2a2ec",
    "storage_bucket": "myshopping-2a2ec.appspot.com"
  },
  "client": [
    {
      "client_info": {
        "mobilesdk_app_id": "1:1063702941408:android:efabac3febc01477c34a85",
        "android_client_info": {
          "package_name": "com.myshopping"
        }
      },
      "oauth_client": [
        {
          "client_id": "1063702941408-kt97s6qs9suheug8jvf1078f8fh9rrqh.apps.googleusercontent.com",
          "client_type": 3
        }
      ],
      "api_key": [
        {
          "current_key": "AIzaSyDkJvBjDO8br8QTWv5Fux_EbzdPk4NvbYg"
        }
      ],
      "services": {
        "appinvite_service": {
          "other_platform_oauth_client": [
            {
              "client_id": "1063702941408-kt97s6qs9suheug8jvf1078f8fh9rrqh.apps.googleusercontent.com",
              "client_type": 3
            }
          ]
        }
      }
    }
  ],
  "configuration_version": "1"
}